vsdfft/__init__.py
vsdfft/_metadata.py
vsdfft/py.typed
vsdfft/spectrum.py
vsdfft/utils.py
vsdfft-1.1.2.dist-info/LICENSE
vsdfft-1.1.2.dist-info/METADATA
vsdfft-1.1.2.dist-info/WHEEL
vsdfft-1.1.2.dist-info/top_level.txt
vsdfft-1.1.2.dist-info/RECORD
