Metadata-Version: 2.1
Name: vsdfft
Version: 1.1.2
Summary: Collection of Discrete/Fast Fourier Transform VapourSynth functions
Author: Setsugen no ao
Author-email: setsugen@setsugen.dev
Maintainer: Setsugen no ao
Maintainer-email: setsugen@setsugen.dev
Project-URL: Source Code, https://github.com/Jaded-Encoding-Thaumaturgy/vs-dfft
Project-URL: Contact, https://discord.gg/XTpc6Fa9eB
Classifier: Programming Language :: Python :: 3
Classifier: License :: OSI Approved :: MIT License
Classifier: Operating System :: OS Independent
Requires-Python: >=3.10
License-File: LICENSE
Requires-Dist: VapourSynth >=68
Requires-Dist: numpy >=1.22.3
Requires-Dist: pyFFTW >=0.13.0
